easymodels/__init__.py
singularitytechnologies.easymodels-0.1.13.dev0.dist-info/DESCRIPTION.rst
singularitytechnologies.easymodels-0.1.13.dev0.dist-info/METADATA
singularitytechnologies.easymodels-0.1.13.dev0.dist-info/RECORD
singularitytechnologies.easymodels-0.1.13.dev0.dist-info/WHEEL
singularitytechnologies.easymodels-0.1.13.dev0.dist-info/metadata.json
singularitytechnologies.easymodels-0.1.13.dev0.dist-info/top_level.txt
