Metadata-Version: 2.0
Name: singularitytechnologies.easymodels
Version: 0.1.13.dev0
Summary: Easy to use Machine Learning training classes
Home-page: https://github.com/singularitydigitaltechnologies/easymodels
Author: Sam Lacey
Author-email: sam.lacey@singularity-technologies.io
License: UNKNOWN
Platform: UNKNOWN
Classifier: Programming Language :: Python :: 3
Classifier: License :: OSI Approved :: GNU General Public License v3 (GPLv3)
Classifier: Operating System :: OS Independent
